intercept/__init__.py
intercept/api_handler.py
intercept/client.py
intercept/data_format.py
intercept/events.py
intercept/utils.py
intercept.py-0.2.0.dist-info/LICENSE
intercept.py-0.2.0.dist-info/METADATA
intercept.py-0.2.0.dist-info/WHEEL
intercept.py-0.2.0.dist-info/top_level.txt
intercept.py-0.2.0.dist-info/RECORD
