Metadata-Version: 2.1
Name: intercept.py
Version: 0.2.0
Summary: Python library for intercept, a game by bubmet
Home-page: https://github.com/martmists/intercept.py
Author: martmists
Author-email: mail@martmists.com
Maintainer: martmists
Maintainer-email: mail@martmists.com
License: MIT
Keywords: game,intercept,asyncio,trio,curio,anyio
Platform: UNKNOWN
Classifier: Development Status :: 4 - Beta
Classifier: Environment :: Console
Classifier: Intended Audience :: Developers
Classifier: License :: OSI Approved :: MIT License
Classifier: Operating System :: OS Independent
Classifier: Programming Language :: Python :: 3
Classifier: Programming Language :: Python :: 3.6
Classifier: Programming Language :: Python :: 3.7
Classifier: Framework :: AsyncIO
Classifier: Topic :: Games/Entertainment
Classifier: Topic :: Communications :: Chat
Classifier: Topic :: Software Development :: Libraries :: Python Modules
Requires-Python: >=3.6
Requires-Dist: anyio
Requires-Dist: colorama
